LICENSE
MANIFEST.in
README.md
pyproject.toml
dnv_bladed_results/__init__.py
dnv_bladed_results.egg-info/PKG-INFO
dnv_bladed_results.egg-info/SOURCES.txt
dnv_bladed_results.egg-info/dependency_links.txt
dnv_bladed_results.egg-info/requires.txt
dnv_bladed_results.egg-info/top_level.txt
dnv_bladed_results/UsageExamples/ResultsApi_BasicOperations.py
dnv_bladed_results/UsageExamples/ResultsApi_Charting2D.py
dnv_bladed_results/UsageExamples/ResultsApi_Charting3D.py
dnv_bladed_results/UsageExamples/ResultsApi_ExceptionHandling.py
dnv_bladed_results/UsageExamples/ResultsApi_FindRuns.py
dnv_bladed_results/UsageExamples/ResultsApi_FindRunsUsingGenerator.py
dnv_bladed_results/UsageExamples/ResultsApi_GroupMetadata.py
dnv_bladed_results/UsageExamples/ResultsApi_PostProcessing.py
dnv_bladed_results/UsageExamples/ResultsApi_RunMetadata.py
dnv_bladed_results/UsageExamples/ResultsApi_VariableData_ExportHDF5.py
dnv_bladed_results/UsageExamples/ResultsApi_VariableData_ExportMatlab.py
dnv_bladed_results/UsageExamples/ResultsApi_VariableData_ReadBasic.py
dnv_bladed_results/UsageExamples/ResultsApi_VariableData_ReadExtended.py
dnv_bladed_results/UsageExamples/ResultsApi_VariableMetadata.py
dnv_bladed_results/UsageExamples/ResultsApi_VariableStats.py
dnv_bladed_results/UsageExamples/ResultsApi_WriteGroup.py
dnv_bladed_results/UsageExamples/__init__.py
dnv_bladed_results/UsageExamples/Runs/demo/PP/bstats/bstats.$01
dnv_bladed_results/UsageExamples/Runs/demo/PP/bstats/bstats.$PJ
dnv_bladed_results/UsageExamples/Runs/demo/PP/bstats/bstats.$TE
dnv_bladed_results/UsageExamples/Runs/demo/PP/bstats/bstats.$VE
dnv_bladed_results/UsageExamples/Runs/demo/PP/bstats/bstats.$me
dnv_bladed_results/UsageExamples/Runs/demo/PP/bstats/bstats.%01
dnv_bladed_results/UsageExamples/Runs/demo/PP/rainflow/rainflow.$11
dnv_bladed_results/UsageExamples/Runs/demo/PP/rainflow/rainflow.$12
dnv_bladed_results/UsageExamples/Runs/demo/PP/rainflow/rainflow.$13
dnv_bladed_results/UsageExamples/Runs/demo/PP/rainflow/rainflow.$19
dnv_bladed_results/UsageExamples/Runs/demo/PP/rainflow/rainflow.$PJ
dnv_bladed_results/UsageExamples/Runs/demo/PP/rainflow/rainflow.$TE
