Metadata-Version: 2.1
Name: dnv_bladed_results
Version: 2.0.0
Summary: An API for working with Bladed results.
Author-email: DNV <renewables.support@dnv.com>
License: MIT License
Project-URL: homepage, https://www.dnv.com/software/services/bladed/
Keywords: bladed,results
Classifier: Operating System :: Microsoft :: Windows
Classifier: Programming Language :: Python :: 3
Classifier: Programming Language :: Python :: 3.9
Classifier: Programming Language :: Python :: 3.10
Classifier: Programming Language :: Python :: 3.11
Classifier: Programming Language :: Python :: 3.12
Requires-Python: >=3.9
License-File: LICENSE
Requires-Dist: numpy==1.*,>=1.26.4
